gen3_validator/__init__.py
gen3_validator/dict.py
gen3_validator/resolve_schema.py
gen3_validator/validate.py
gen3_validator-2.0.0.dist-info/METADATA
gen3_validator-2.0.0.dist-info/WHEEL
gen3_validator-2.0.0.dist-info/licenses/LICENSE
gen3_validator-2.0.0.dist-info/RECORD
