Metadata-Version: 2.4
Name: gen3_validator
Version: 2.0.0
Summary: Comprehensive toolkit for resolving Gen3 JSON schemas, validating JSON metadata against schemas, and verifying linkage integrity between data nodes. Includes utilities for parsing Excel metadata templates, generating linkage configuration maps, orchestrating schema validation, and producing detailed validation reports and statistics
License: Apache 2.0
License-File: LICENSE
Author: JoshuaHarris391
Author-email: harjo391@gmail.com
Requires-Python: >=3.9.5
Classifier: License :: Other/Proprietary License
Classifier: Programming Language :: Python :: 3
Classifier: Programming Language :: Python :: 3.10
Classifier: Programming Language :: Python :: 3.11
Classifier: Programming Language :: Python :: 3.12
Classifier: Programming Language :: Python :: 3.13
Classifier: Programming Language :: Python :: 3.14
Requires-Dist: jsonschema (>=4.23.0)
Requires-Dist: numpy (>=1.26.0,<2.0.0)
Requires-Dist: openpyxl (>=3.1.5,<4.0.0)
Requires-Dist: pandas (>=2.2.3)
Requires-Dist: pydantic (>=2.10.6)
Requires-Dist: pyfakefs (>=4.7.0)
Requires-Dist: pytest (>=8.3.4)
Requires-Dist: pyyaml (>=6.0.3,<7.0.0)
Requires-Dist: shibuya
Requires-Dist: sphinx
Requires-Dist: typing (>=3.7.4.3)
Requires-Dist: uuid (>=1.30)
